{
	"status": "public",
	"title": "The Carmen Murray Show",
	"host": "Carmen Murray",
	"coverFileName": "carmen-murray-show-f.jpg",
	"filterKeywords": "carmen murray show",
	"agreement": "yes",
	"playlistUrl": "https://pod.link/tcms",
	"websiteUrl": "http://www.carmenmurray.com",
	"email": "hello@carmenmurray.com",
	"emailAgreement": "hello@carmenmurray.com",
	"twitterUrl": "https://twitter.com/CarmenMurraySA",
	"linkedinUrl": "https://www.linkedin.com/in/carmen-murray-787b2323",
	"instagramUrl": "https://www.instagram.com/iamcarmenmurray",
	"tumblrUrl": "https://carmenmurrayblog.tumblr.com",
	"rssUrl": "https://podcaststudios.co.za/rss/thecarmenmurrayshow.xml",
	"description": "<p>Are you looking to broaden your horizons, to stay relevant and become Future Fit?</p><p>Do you want to fuel your creativity and inspire Innovation? Or... are you simply looking to put the \"kapow\" back into your business?</p><p>Then look no further. Join Carmen Murray, Entrepreneur, Innovator and Tech Fundi, with her big personality and presentation style, as she interviews celebrities, alchemists, news-makers and business experts to discover the stories behind their success.</p><p><i>The Carmen Murray Show</i> will open your mind and help you turn knowledge into magic. Let knowledge be your Superpower!</p>"
 }
