{	
	"status": "comingSoon",
	"title": "Shotgun Story",
	"host": "Shotgun Tori",
	"coverFileName": "shotgun-story-000a.jpg",
	"filterKeywords": "shotgun tori story music",
	"donateLink": "",
	"genre1": "",
	"genre2": "",
	"genre3": "",
	"agreement": "yes",
	"whatsappNumber": "",
	"playlistUrl": "https://podlink.to/shotgun",
	"websiteUrl": "",
	"email": "shotguntori@gmail.com",
	"emailAgreement": "shotguntori@gmail.com",
	"facebookUrl": "",
	"twitterUrl": "",
	"linkedinUrl": "",
	"instagramUrl": "",
	"tumblrUrl": "",
	"youtubeUrl": "",
	"rssUrl": "",
	"extraButtonLabel": "",
	"extraButtonUrl": "",
	"buyLink1Label": "",
	"buyLink1Url": "",
	"buyLink2Label": "",
	"buyLink2Url": "",
	"buyLink3Label": "",
	"buyLink3Url": "",
	"description": "<h3>A songwriter's search for meaning...</h3><p>"
}