{	
	"status": "public",
	"title": "Vox Audiobooks",
	"host": "Find your Audiobook voice",
	"coverFileName": "vox-audiobooks-000a.jpg",
	"filterKeywords": "vox audiobook voice narrate",
	"donateLink": "http://paypal.me/gakennedy",
	"genre1": "",
	"genre2": "",
	"genre3": "",
	"agreement": "yes",
	"whatsappNumber": "27832271409",
	"playlistUrl": "https://pod.link/audiobooks",
	"websiteUrl": "https://vox.org.za",
	"email": "mail@vox.org.za",
	"emailAgreement": "mail@vox.org.za",
	"facebookUrl": "",
	"twitterUrl": "",
	"linkedinUrl": "",
	"instagramUrl": "",
	"tumblrUrl": "",
	"youtubeUrl": "",
	"rssUrl": "https://iono.fm/rss/chan/6150",
	"extraButtonLabel": "",
	"extraButtonUrl": "",
	"buyLink1Label": "",
	"buyLink1Url": "",
	"buyLink2Label": "",
	"buyLink2Url": "",
	"buyLink3Label": "",
	"buyLink3Url": "",
	"description": "<h3>Are you looking for the narrator for your next audiobook?</h3><p>Your search is over!</p><p>Our selection of narrators deliver professional performances for every kind of book you can imagine.</p><p>To be understood, you must first be heard."
}